[
  {
    "name": "T-Bug",
    "color": "b60205",
    "description": "type: bug - 不具合の報告・修正",
    "ref": "T-Bug"
  },
  {
    "name": "T-Feature",
    "color": "1d76db",
    "description": "type: feature - 新機能の追加",
    "ref": "T-Feature"
  },
  {
    "name": "T-Enhancement",
    "color": "1d76db",
    "description": "type: enhancement - 既存機能の拡張・改善",
    "ref": "T-Enhancement"
  },
  {
    "name": "T-Refactor",
    "color": "1d76db",
    "description": "type: refactor - 構造改善・リファクタリング",
    "ref": "T-Refactor"
  },
  {
    "name": "T-Documentation",
    "color": "1d76db",
    "description": "type: documentation - ドキュメントの作成・更新",
    "ref": "T-Documentation"
  },
  {
    "name": "T-Chore",
    "color": "1d76db",
    "description": "type: chore - 雑務・メンテ作業",
    "ref": "T-Chore"
  },

  {
    "name": "A-App",
    "color": "0f302b",
    "description": "area: app - アプリケーション全体",
    "ref": "A-App"
  },
  {
    "name": "A-Backend",
    "color": "0f302b",
    "description": "area: backend - バックエンド",
    "ref": "A-Backend"
  },
  {
    "name": "A-Web",
    "color": "0f302b",
    "description": "area: web - Web フロント",
    "ref": "A-Web"
  },
  {
    "name": "A-Mobile",
    "color": "0f302b",
    "description": "area: mobile - モバイルアプリ",
    "ref": "A-Mobile"
  },
  {
    "name": "A-Packages",
    "color": "0f302b",
    "description": "area: packages - パッケージ",
    "ref": "A-Packages"
  },

  {
    "name": "P-Critical",
    "color": "f01cd9",
    "description": "priority: critical - 最優先・即時対応",
    "ref": "P-Critical"
  },
  {
    "name": "P-High",
    "color": "f01cd9",
    "description": "priority: high - 高優先",
    "ref": "P-High"
  },
  {
    "name": "P-Medium",
    "color": "f01cd9",
    "description": "priority: medium - 中優先",
    "ref": "P-Medium"
  },
  {
    "name": "P-Low",
    "color": "f01cd9",
    "description": "priority: low - 低優先",
    "ref": "P-Low"
  },

  {
    "name": "S-Epic",
    "color": "fbca04",
    "description": "scope: epic - 複数Issueを束ねる大項目",
    "ref": "S-Epic"
  },
  {
    "name": "S-Task",
    "color": "fbca04",
    "description": "scope: task - 通常の作業単位",
    "ref": "S-Task"
  },
  {
    "name": "S-Hotfix",
    "color": "b60205",
    "description": "scope: hotfix - 緊急修正",
    "ref": "S-Hotfix"
  }
]
