{
  "version": "6",
  "dialect": "sqlite",
  "entries": [
    {
      "idx": 0,
      "version": "6",
      "when": 1734532505135,
      "tag": "0000_chilly_mephistopheles",
      "breakpoints": true
    },
    {
      "idx": 1,
      "version": "6",
      "when": 1741265148875,
      "tag": "0001_concerned_vapor",
      "breakpoints": true
    },
    {
      "idx": 2,
      "version": "6",
      "when": 1741266985343,
      "tag": "0002_third_wolverine",
      "breakpoints": true
    },
    {
      "idx": 3,
      "version": "6",
      "when": 1741468212365,
      "tag": "0003_mixed_lord_hawal",
      "breakpoints": true
    },
    {
      "idx": 4,
      "version": "6",
      "when": 1741625220241,
      "tag": "0004_soft_omega_flight",
      "breakpoints": true
    },
    {
      "idx": 5,
      "version": "6",
      "when": 1743236350813,
      "tag": "0005_daffy_slipstream",
      "breakpoints": true
    },
    {
      "idx": 6,
      "version": "6",
      "when": 1745124125654,
      "tag": "0006_acoustic_iron_patriot",
      "breakpoints": true
    },
    {
      "idx": 7,
      "version": "6",
      "when": 1745214719648,
      "tag": "0007_dazzling_bullseye",
      "breakpoints": true
    },
    {
      "idx": 8,
      "version": "6",
      "when": 1745409597336,
      "tag": "0008_lonely_quasimodo",
      "breakpoints": true
    },
    {
      "idx": 9,
      "version": "6",
      "when": 1751489650784,
      "tag": "0009_parched_colleen_wing",
      "breakpoints": true
    },
    {
      "idx": 10,
      "version": "6",
      "when": 1759858850772,
      "tag": "0010_easy_ikaris",
      "breakpoints": true
    },
    {
      "idx": 11,
      "version": "6",
      "when": 1760336772293,
      "tag": "0011_aberrant_shard",
      "breakpoints": true
    },
    {
      "idx": 12,
      "version": "6",
      "when": 1762084238639,
      "tag": "0012_clear_kabuki",
      "breakpoints": true
    },
    {
      "idx": 13,
      "version": "6",
      "when": 1763426603545,
      "tag": "0013_wandering_scream",
      "breakpoints": true
    },
    {
      "idx": 14,
      "version": "6",
      "when": 1765613732201,
      "tag": "0014_peaceful_stingray",
      "breakpoints": true
    },
    {
      "idx": 15,
      "version": "6",
      "when": 1766327984798,
      "tag": "0015_hot_magdalene",
      "breakpoints": true
    },
    {
      "idx": 16,
      "version": "6",
      "when": 1766392921006,
      "tag": "0016_nosy_lady_bullseye",
      "breakpoints": true
    }
  ]
}